{
  "crop_name": "මඤ්ඤොක්කා",
  "scientific_name": null,
  "growing_areas": [
    "Wet Zone",
    "Dry Zone"
  ],
  "growing_seasons": [
    "Year-round",
    "Yala",
    "Maha"
  ],
  "varieties": [
    "MU-51",
    "Kirikawadi",
    "CAR5 555",
    "Suranimala",
    "Swarna",
    "Shani",
    "HORDI-MU-1",
    "HORDI 06"
  ],
  "soil_types": [
    "Well-drained soil",
    "Non-alkaline soil"
  ],
  "altitude_min_m": null,
  "altitude_max_m": 1500.0,
  "temp_min_c": 25.0,
  "temp_max_c": 29.0,
  "rainfall_min_mm": 1000.0,
  "rainfall_max_mm": 1500.0,
  "ph_min": 5.0,
  "ph_max": 6.0,
  "pit_length_cm": null,
  "pit_width_cm": null,
  "row_distance_cm": 90.0,
  "plant_distance_cm": 90.0,
  "fertilizer_schedule": [
    {
      "fertilizer": "Urea",
      "apply_start_weeks_after_planting": 2.14,
      "repeat_count": 1,
      "repeat_interval_weeks": 0.0,
      "quantity_kg_per_ha": 85.0
    },
    {
      "fertilizer": "Triple Super Phosphate",
      "apply_start_weeks_after_planting": 2.14,
      "repeat_count": 1,
      "repeat_interval_weeks": 0.0,
      "quantity_kg_per_ha": 120.0
    },
    {
      "fertilizer": "Muriate of Potash",
      "apply_start_weeks_after_planting": 2.14,
      "repeat_count": 1,
      "repeat_interval_weeks": 0.0,
      "quantity_kg_per_ha": 125.0
    },
    {
      "fertilizer": "Urea",
      "apply_start_weeks_after_planting": 10.8,
      "repeat_count": 1,
      "repeat_interval_weeks": 0.0,
      "quantity_kg_per_ha": 85.0
    },
    {
      "fertilizer": "Muriate of Potash",
      "apply_start_weeks_after_planting": 10.8,
      "repeat_count": 1,
      "repeat_interval_weeks": 0.0,
      "quantity_kg_per_ha": 60.0
    },
    {
      "fertilizer": "Urea",
      "apply_start_weeks_after_planting": 17.3,
      "repeat_count": 1,
      "repeat_interval_weeks": 0.0,
      "quantity_kg_per_ha": 85.0
    },
    {
      "fertilizer": "Muriate of Potash",
      "apply_start_weeks_after_planting": 17.3,
      "repeat_count": 1,
      "repeat_interval_weeks": 0.0,
      "quantity_kg_per_ha": 60.0
    }
  ],
  "pests": [
    {
      "name": "Whiteflies",
      "impact": "Vectors of virus diseases.",
      "solution": "Spray neem solution, cover crop with a living fence like maize, intercrop with maize, spray water on the crop."
    }
  ],
  "diseases": [
    {
      "name": "Cassava Leaf Mosaic Virus (SLCMV)",
      "causal_agent": "Virus",
      "impact": "Yellow-green mosaic patterns on leaves, leaf curling and reduced leaf area, irregular leaf shape, stunting of plants, gradual weakening of plants, and reduced yield.",
      "solution": "No treatment once infected. Use only stem cuttings from healthy plants. Uproot and destroy diseased plants. Remove wild cassava, wild clove, wild rubber, and Kuppamenia from the field. Do not start a new cultivation near a diseased one; first remove all diseased plants from the old cultivation. Always remove weeds around the crop and keep the field clean. Mark diseased plant stems with paint to facilitate removal during harvest."
    },
    {
      "name": "Brown Spot Disease",
      "causal_agent": "Corynespora cassiicola (Mycosphaerella spp. & fungus)",
      "impact": "Brown spots on leaves. Mature lower leaves are usually infected first, with upper leaves also getting infected when damage is severe. Leaves turn yellow and fall off.",
      "solution": "In home gardens, remove and burn infected leaves from the field. In commercial cultivations, when the disease is prevalent in young plants, apply Mancozeb 80% WP (32g per 16-liter tank of water) to leaves to control spread."
    },
    {
      "name": "Root Rot",
      "causal_agent": "Sclerotium spp. fungus",
      "impact": "Rotting of roots and stems of plants in patches. Leaves turn yellow, plant dries up and dies. White fungal mycelium visible at the base of the plant.",
      "solution": "Improve soil drainage. If it's a paddy field, improve drainage by digging deep canals. Uproot diseased plants along with soil and remove from the field at the early stages of the disease."
    }
  ],
  "expected_harvest_kg_per_ha": 37500.0
}
